[
  {
    "position": 1,
    "equipe": "Paris SG",
    "matchs_joues": 31,
    "gagnes": 22,
    "nuls": 4,
    "perdus": 5,
    "buts_marques": 70,
    "buts_encaisses": 27,
    "difference": 43,
    "points": 70,
    "positionStatus": "UEFA Champions League"
  },
  {
    "position": 2,
    "equipe": "RC Lens",
    "matchs_joues": 31,
    "gagnes": 20,
    "nuls": 4,
    "perdus": 7,
    "buts_marques": 61,
    "buts_encaisses": 33,
    "difference": 28,
    "points": 64,
    "positionStatus": "UEFA Champions League"
  },
  {
    "position": 3,
    "equipe": "Ol. Lyonnais",
    "matchs_joues": 32,
    "gagnes": 18,
    "nuls": 6,
    "perdus": 8,
    "buts_marques": 52,
    "buts_encaisses": 34,
    "difference": 18,
    "points": 60,
    "positionStatus": "UEFA Champions League"
  },
  {
    "position": 4,
    "equipe": "LOSC Lille",
    "matchs_joues": 32,
    "gagnes": 17,
    "nuls": 7,
    "perdus": 8,
    "buts_marques": 51,
    "buts_encaisses": 35,
    "difference": 16,
    "points": 58,
    "positionStatus": "Barrages Champions League"
  },
  {
    "position": 5,
    "equipe": "Stade Rennais",
    "matchs_joues": 32,
    "gagnes": 16,
    "nuls": 8,
    "perdus": 8,
    "buts_marques": 56,
    "buts_encaisses": 46,
    "difference": 10,
    "points": 56,
    "positionStatus": "UEFA Europa League"
  },
  {
    "position": 6,
    "equipe": "Monaco",
    "matchs_joues": 32,
    "gagnes": 16,
    "nuls": 6,
    "perdus": 10,
    "buts_marques": 56,
    "buts_encaisses": 48,
    "difference": 8,
    "points": 54,
    "positionStatus": "Barrages Conference League"
  },
  {
    "position": 7,
    "equipe": "Marseille",
    "matchs_joues": 32,
    "gagnes": 16,
    "nuls": 5,
    "perdus": 11,
    "buts_marques": 59,
    "buts_encaisses": 44,
    "difference": 15,
    "points": 53,
    "positionStatus": ""
  },
  {
    "position": 8,
    "equipe": "R. Strasbourg",
    "matchs_joues": 31,
    "gagnes": 13,
    "nuls": 7,
    "perdus": 11,
    "buts_marques": 50,
    "buts_encaisses": 41,
    "difference": 9,
    "points": 46,
    "positionStatus": ""
  },
  {
    "position": 9,
    "equipe": "FC Lorient",
    "matchs_joues": 32,
    "gagnes": 10,
    "nuls": 12,
    "perdus": 10,
    "buts_marques": 44,
    "buts_encaisses": 49,
    "difference": -5,
    "points": 42,
    "positionStatus": ""
  },
  {
    "position": 10,
    "equipe": "Toulouse",
    "matchs_joues": 32,
    "gagnes": 11,
    "nuls": 8,
    "perdus": 13,
    "buts_marques": 45,
    "buts_encaisses": 45,
    "difference": 0,
    "points": 41,
    "positionStatus": ""
  },
  {
    "position": 11,
    "equipe": "Paris FC",
    "matchs_joues": 32,
    "gagnes": 10,
    "nuls": 11,
    "perdus": 11,
    "buts_marques": 44,
    "buts_encaisses": 47,
    "difference": -3,
    "points": 41,
    "positionStatus": ""
  },
  {
    "position": 12,
    "equipe": "Stade Brestois",
    "matchs_joues": 31,
    "gagnes": 10,
    "nuls": 8,
    "perdus": 13,
    "buts_marques": 41,
    "buts_encaisses": 51,
    "difference": -10,
    "points": 38,
    "positionStatus": ""
  },
  {
    "position": 13,
    "equipe": "Angers SCO",
    "matchs_joues": 32,
    "gagnes": 9,
    "nuls": 7,
    "perdus": 16,
    "buts_marques": 27,
    "buts_encaisses": 46,
    "difference": -19,
    "points": 34,
    "positionStatus": ""
  },
  {
    "position": 14,
    "equipe": "Le Havre AC",
    "matchs_joues": 32,
    "gagnes": 6,
    "nuls": 14,
    "perdus": 12,
    "buts_marques": 30,
    "buts_encaisses": 43,
    "difference": -13,
    "points": 32,
    "positionStatus": ""
  },
  {
    "position": 15,
    "equipe": "OGC Nice",
    "matchs_joues": 32,
    "gagnes": 7,
    "nuls": 10,
    "perdus": 15,
    "buts_marques": 36,
    "buts_encaisses": 58,
    "difference": -22,
    "points": 31,
    "positionStatus": ""
  },
  {
    "position": 16,
    "equipe": "AJ Auxerre",
    "matchs_joues": 32,
    "gagnes": 6,
    "nuls": 10,
    "perdus": 16,
    "buts_marques": 30,
    "buts_encaisses": 43,
    "difference": -13,
    "points": 28,
    "positionStatus": "Barrages Ligue 2"
  },
  {
    "position": 17,
    "equipe": "FC Nantes",
    "matchs_joues": 32,
    "gagnes": 5,
    "nuls": 8,
    "perdus": 19,
    "buts_marques": 29,
    "buts_encaisses": 51,
    "difference": -22,
    "points": 23,
    "positionStatus": "Ligue 2"
  },
  {
    "position": 18,
    "equipe": "FC Metz",
    "matchs_joues": 32,
    "gagnes": 3,
    "nuls": 7,
    "perdus": 22,
    "buts_marques": 32,
    "buts_encaisses": 72,
    "difference": -40,
    "points": 16,
    "positionStatus": "Ligue 2"
  }
]